spotler_sdk/__init__.py
spotler_sdk/models.py
spotler_sdk/sdk.py
spotler_sdk-0.3.2.dist-info/METADATA
spotler_sdk-0.3.2.dist-info/WHEEL
spotler_sdk-0.3.2.dist-info/RECORD
